easy_opencv/__init__.py
easy_opencv/drawing_operations.py
easy_opencv/feature_detection.py
easy_opencv/filters.py
easy_opencv/image_operations.py
easy_opencv/image_processing.py
easy_opencv/object_detection.py
easy_opencv/transformations.py
easy_opencv/utils.py
easy_opencv/video_operations.py
easy_opencv_wrapper-1.0.3.dist-info/licenses/LICENSE
easy_opencv_wrapper-1.0.3.dist-info/METADATA
easy_opencv_wrapper-1.0.3.dist-info/WHEEL
easy_opencv_wrapper-1.0.3.dist-info/top_level.txt
easy_opencv_wrapper-1.0.3.dist-info/RECORD
