Metadata-Version: 2.4
Name: easy-opencv-wrapper
Version: 1.0.3
Summary: A simplified and intuitive OpenCV wrapper that reduces code complexity by 50-70% for common computer vision tasks
Home-page: https://github.com/aksh-agrawal/easy-opencv-wrapper
Author: Aksh Agrawal
Author-email: Aksh Agrawal <akshagr10@gmail.com>
Maintainer-email: Aksh Agrawal <akshagr10@gmail.com>
License-Expression: MIT
Project-URL: Homepage, https://github.com/aksh-agrawal/easy-opencv-wrapper
Project-URL: Documentation, https://github.com/aksh-agrawal/easy-opencv-wrapper#readme
Project-URL: Repository, https://github.com/aksh-agrawal/easy-opencv-wrapper.git
Project-URL: Issues, https://github.com/aksh-agrawal/easy-opencv-wrapper/issues
Project-URL: Changelog, https://github.com/aksh-agrawal/easy-opencv-wrapper/releases
Keywords: opencv,computer-vision,image-processing,cv,wrapper,simplified,easy
Classifier: Development Status :: 5 - Production/Stable
Classifier: Intended Audience :: Developers
Classifier: Intended Audience :: Education
Classifier: Intended Audience :: Science/Research
Classifier: Operating System :: OS Independent
Classifier: Programming Language :: Python :: 3
Classifier: Programming Language :: Python :: 3.7
Classifier: Programming Language :: Python :: 3.8
Classifier: Programming Language :: Python :: 3.9
Classifier: Programming Language :: Python :: 3.10
Classifier: Programming Language :: Python :: 3.11
Classifier: Programming Language :: Python :: 3.12
Classifier: Topic :: Scientific/Engineering :: Image Processing
Classifier: Topic :: Software Development :: Libraries :: Python Modules
Classifier: Topic :: Multimedia :: Graphics :: Capture
Classifier: Topic :: Multimedia :: Video :: Capture
Requires-Python: >=3.7
License-File: LICENSE
Requires-Dist: opencv-python>=4.5.0
Requires-Dist: numpy>=1.19.0
Requires-Dist: pillow>=8.0.0
Provides-Extra: dev
Requires-Dist: pytest>=6.0; extra == "dev"
Requires-Dist: pytest-cov>=2.0; extra == "dev"
Requires-Dist: black>=21.0; extra == "dev"
Requires-Dist: flake8>=3.8; extra == "dev"
Requires-Dist: mypy>=0.812; extra == "dev"
Dynamic: author
Dynamic: home-page
Dynamic: license-file
Dynamic: requires-python
